malnet_core-0.1.1-py3.7-nspkg.pth
malnet/core/__init__.py
malnet/core/config.py
malnet/core/exception.py
malnet/core/idgen.py
malnet/core/utils.py
malnet/core/data/dev.conf
malnet/core/data/prud.conf
malnet_core-0.1.1.dist-info/LICENSE
malnet_core-0.1.1.dist-info/METADATA
malnet_core-0.1.1.dist-info/WHEEL
malnet_core-0.1.1.dist-info/namespace_packages.txt
malnet_core-0.1.1.dist-info/top_level.txt
malnet_core-0.1.1.dist-info/zip-safe
malnet_core-0.1.1.dist-info/RECORD
