Metadata-Version: 2.1
Name: malnet-core
Version: 0.1.1
Summary: malnet backend core package
Home-page: https://git.kongkongss.com/jyk/jyk-time
Author: Yongkang Jiang
Author-email: jyk.kongkong@gmail.com
License: MIT
Platform: UNKNOWN
Classifier: Programming Language :: Python :: 3.7
Classifier: License :: OSI Approved :: MIT License
Classifier: Operating System :: OS Independent
Requires-Python: >=3.7
Requires-Dist: toml (>=0.10.1)
